mycalc/calculator.py
ahdmycalc-0.0.5.6.dist-info/METADATA
ahdmycalc-0.0.5.6.dist-info/WHEEL
ahdmycalc-0.0.5.6.dist-info/top_level.txt
ahdmycalc-0.0.5.6.dist-info/RECORD
