Metadata-Version: 2.1
Name: ahdmycalc
Version: 0.0.5.6
Summary: nice calculator
Home-page: https://github.com/LEEhodu/calc001
Download-URL: https://github.com/LEEhodu/calc001
Author: smlee
Classifier: Programming Language :: Python :: 3
